GymBuddyApp/README.md
GymBuddyApp/db.json
GymBuddyApp/db.sqlite3
GymBuddyApp/manage.py
GymBuddyApp/requirements.txt
GymBuddyApp/gymBuddyApp/__init__.py
GymBuddyApp/gymBuddyApp/asgi.py
GymBuddyApp/gymBuddyApp/settings.py
GymBuddyApp/gymBuddyApp/urls.py
GymBuddyApp/gymBuddyApp/wsgi.py
GymBuddyApp/pages/__init__.py
GymBuddyApp/pages/admin.py
GymBuddyApp/pages/apps.py
GymBuddyApp/pages/models.py
GymBuddyApp/pages/tests.py
GymBuddyApp/pages/urls.py
GymBuddyApp/pages/views.py
GymBuddyApp/pages/migrations/__init__.py
GymBuddyApp/pages/static/pages/main.css
GymBuddyApp/pages/templates/pages/base.html
GymBuddyApp/pages/templates/pages/home.html
GymBuddyApp/static/Source/Magnific-Popup-master.zip
GymBuddyApp/static/Source/OwlCarousel2-2.3.4.zip
GymBuddyApp/static/Source/SlickNav-master.zip
GymBuddyApp/static/Source/bootstrap-4.4.1-dist.zip
GymBuddyApp/static/Source/font-awesome-4.7.0.zip
GymBuddyApp/static/Source/sass.zip
GymBuddyApp/static/css/style.css
GymBuddyApp/static/img/Macro-Graphic.png
GymBuddyApp/static/img/about-pic.jpg
GymBuddyApp/static/img/exercise-filler.jpg
GymBuddyApp/static/img/gymWide.jpg
GymBuddyApp/static/img/logo.png
GymBuddyApp/static/img/logo1.png
GymBuddyApp/static/img/logo2.png
GymBuddyApp/static/img/meals_filler.png
GymBuddyApp/static/img/weight-filler.png
GymBuddyApp/static/media/profile_pics/default.jpg
GymBuddyApp/users/Exercises.json
GymBuddyApp/users/Meals.json
GymBuddyApp/users/__init__.py
GymBuddyApp/users/admin.py
GymBuddyApp/users/apps.py
GymBuddyApp/users/forms.py
GymBuddyApp/users/models.py
GymBuddyApp/users/signals.py
GymBuddyApp/users/tests.py
GymBuddyApp/users/views.py
GymBuddyApp/users/migrations/__init__.py
GymBuddyApp/users/templates/users/base.html
GymBuddyApp/users/templates/users/exercises.html
GymBuddyApp/users/templates/users/login.html
GymBuddyApp/users/templates/users/logout.html
GymBuddyApp/users/templates/users/macros.html
GymBuddyApp/users/templates/users/meals.html
GymBuddyApp/users/templates/users/password_reset.html
GymBuddy-2.1.7.dist-info/METADATA
GymBuddy-2.1.7.dist-info/WHEEL
GymBuddy-2.1.7.dist-info/entry_points.txt
GymBuddy-2.1.7.dist-info/top_level.txt
GymBuddy-2.1.7.dist-info/RECORD
